{"id":"b2-20","track":"advanced","band":"B2","order":48,"title":{"en":"B2 · pack 20","zh":"B2 · 第20组"},"words":[{"w":"remark","pos":"n","cefr":"B2","def":"something that you say or write which expresses an opinion, a thought, etc. about somebody/something","example":"to make a remark"},{"w":"remarkable","pos":"adj","cefr":"B2","def":"unusual or surprising in a way that causes people to take notice","example":"a remarkable achievement/career/talent"},{"w":"remarkably","pos":"v","cefr":"B2","def":"in a way that is unusual or surprising and causes people to take notice","example":"The car is in remarkably good condition for its age."},{"w":"reorganise","pos":"v","cefr":"B2","def":"","example":""},{"w":"reorganize","pos":"v","cefr":"B2","def":"","example":""},{"w":"repaint","pos":"n","cefr":"B2","def":"","example":""},{"w":"repertoire","pos":"n","cefr":"B2","def":"","example":""},{"w":"repetition","pos":"n","cefr":"B2","def":"","example":""},{"w":"replica","pos":"n","cefr":"B2","def":"","example":""},{"w":"reporting","pos":"n","cefr":"B2","def":"the presenting of and writing about news on television and radio, and in newspapers","example":"accurate/balanced/objective reporting"},{"w":"representative","pos":"n","cefr":"B2","def":"typical of a particular group of people; that is a typical example of something","example":"Is a questionnaire answered by 500 people truly representative of the population as a whole?"},{"w":"repress","pos":"v","cefr":"B2","def":"","example":""},{"w":"repression","pos":"n","cefr":"B2","def":"","example":""},{"w":"reprint","pos":"n","cefr":"B2","def":"","example":""},{"w":"reprove","pos":"v","cefr":"B2","def":"","example":""},{"w":"reputation","pos":"n","cefr":"B2","def":"the opinion that people have about what somebody/something is like, based on what has happened in the past","example":"to have a good/bad reputation"},{"w":"requirement","pos":"n","cefr":"B2","def":"something that you need or want","example":"the basic requirements of life"},{"w":"rescue","pos":"n","cefr":"B2","def":"the act of saving somebody/something from a dangerous or difficult situation; the fact of being saved","example":"We had given up hope of rescue."},{"w":"reserve","pos":"n","cefr":"B2","def":"a supply of something that is available to be used in the future or when it is needed","example":"cash/foreign currency reserves"},{"w":"resident","pos":"adj","cefr":"B2","def":"living in a particular place","example":"the town’s resident population (= not tourists or visitors)"},{"w":"resign","pos":"v","cefr":"B2","def":"to officially tell somebody that you are leaving your job, an organization, etc.","example":"She was forced to resign due to ill health."},{"w":"resist","pos":"v","cefr":"B2","def":"to refuse to accept something and try to stop it from happening","example":"resist something, They are determined to resist pressure to change the law."},{"w":"resolution","pos":"n","cefr":"B2","def":"a definite decision to do or not to do something","example":"Have you made any New Year's resolutions (= for example, to give up smoking from 1 January)?"},{"w":"resolve","pos":"v","cefr":"B2","def":"to find an acceptable solution to a problem or difficulty","example":"resolve something, to resolve an issue/a dispute/a conflict/a crisis"},{"w":"resonant","pos":"adj","cefr":"B2","def":"","example":""},{"w":"resort","pos":"n","cefr":"B2","def":"a place where a lot of people go on holiday","example":"seaside/mountain resorts"},{"w":"respectably","pos":"v","cefr":"B2","def":"","example":""},{"w":"respected","pos":"adj","cefr":"B2","def":"","example":""},{"w":"respiration","pos":"n","cefr":"B2","def":"","example":""},{"w":"respiratory","pos":"adj","cefr":"B2","def":"","example":""},{"w":"restore","pos":"v","cefr":"B2","def":"to bring back a situation or feeling that existed before","example":"restore something, The measures are intended to restore public confidence in the economy."},{"w":"restrict","pos":"v","cefr":"B2","def":"to limit the size, amount or range of something","example":"restrict something to something, Speed is restricted to 30 mph in towns."},{"w":"restriction","pos":"n","cefr":"B2","def":"a rule or law that limits what you can do or what can happen","example":"import/speed/travel restrictions"},{"w":"retail","pos":"n","cefr":"B2","def":"the selling of goods to the public, usually through shops","example":"The recommended retail price is £9.99."},{"w":"retailer","pos":"n","cefr":"B2","def":"","example":""},{"w":"retain","pos":"v","cefr":"B2","def":"to keep something; to continue to have something","example":"to retain your independence"},{"w":"retard","pos":"v","cefr":"B2","def":"","example":""},{"w":"retina","pos":"n","cefr":"B2","def":"","example":""},{"w":"retirement","pos":"n","cefr":"B2","def":"the fact of leaving your job and stopping work, usually because you have reached a particular age; the time when you do this","example":"At 60, he was now approaching retirement."},{"w":"reveal","pos":"v","cefr":"B2","def":"to make something known to somebody","example":"reveal something, to reveal a secret"},{"w":"revenue","pos":"n","cefr":"B2","def":"the money that a government receives from taxes or that an organization, etc. receives from its business","example":"The government is currently facing a shortfall in tax revenue."},{"w":"reverence","pos":"n","cefr":"B2","def":"","example":""},{"w":"revision","pos":"n","cefr":"B2","def":"a change or set of changes to something","example":"He made some minor revisions to the report before printing it out."},{"w":"revolution","pos":"n","cefr":"B2","def":"an attempt, by a large number of people, to change the government of a country, especially by violent action","example":"a socialist revolution"},{"w":"revolutionise","pos":"v","cefr":"B2","def":"","example":""},{"w":"revolutionize","pos":"v","cefr":"B2","def":"","example":""},{"w":"revolve","pos":"v","cefr":"B2","def":"","example":""},{"w":"reward","pos":"n","cefr":"B2","def":"a thing that you are given because you have done something good, worked hard, etc.","example":"a financial reward"},{"w":"rhinoceros","pos":"n","cefr":"B2","def":"","example":""},{"w":"rhyme","pos":"v","cefr":"B2","def":"","example":""},{"w":"rhythm","pos":"n","cefr":"B2","def":"a strong regular repeated pattern of sounds or movements","example":"to dance to the rhythm of the music"},{"w":"rhythmic","pos":"adj","cefr":"B2","def":"","example":""},{"w":"rib","pos":"n","cefr":"B2","def":"","example":""},{"w":"rid","pos":"v","cefr":"B2","def":"to be free of somebody/something that has been annoying you or that you do not want","example":"She wanted to be rid of her parents and their authority."},{"w":"riddle","pos":"n","cefr":"B2","def":"","example":""},{"w":"rider","pos":"n","cefr":"B2","def":"","example":""},{"w":"ridge","pos":"n","cefr":"B2","def":"","example":""},{"w":"ridiculous","pos":"adj","cefr":"B2","def":"very silly or unreasonable","example":"I look ridiculous in this hat."},{"w":"righteousness","pos":"n","cefr":"B2","def":"","example":""},{"w":"rightly","pos":"v","cefr":"B2","def":"","example":""},{"w":"rim","pos":"n","cefr":"B2","def":"","example":""},{"w":"risky","pos":"adj","cefr":"B2","def":"involving the possibility of something bad happening","example":"Life as an aid worker can be a risky business (= dangerous)."},{"w":"rite","pos":"n","cefr":"B2","def":"","example":""},{"w":"rival","pos":"n","cefr":"B2","def":"competing with another person, company, thing, etc.","example":"a rival bid/claim/offer"},{"w":"roam","pos":"n","cefr":"B2","def":"","example":""},{"w":"roar","pos":"v","cefr":"B2","def":"","example":""},{"w":"roast","pos":"adj","cefr":"B2","def":"","example":""},{"w":"rob","pos":"v","cefr":"B2","def":"to steal money or property from a person or place","example":"to rob a bank"},{"w":"robbery","pos":"n","cefr":"B2","def":"the crime of stealing money or goods from a bank, shop, person, etc., especially using violence or threats","example":"armed robbery (= using a gun, knife, etc.)"},{"w":"rocket","pos":"n","cefr":"B2","def":"a spacecraft in the shape of a tube that is driven by a stream of gases let out behind it when fuel is burned inside","example":"a space rocket"},{"w":"rocky","pos":"adj","cefr":"B2","def":"","example":""},{"w":"romance","pos":"n","cefr":"B2","def":"an exciting, usually short, relationship between two people who are in love with each other","example":"a holiday romance"},{"w":"roommate","pos":"n","cefr":"B2","def":"","example":""},{"w":"root","pos":"n","cefr":"B2","def":"the part of a plant that grows under the ground and takes in water and minerals that it sends to the rest of the plant","example":"deep spreading roots"},{"w":"rose","pos":"n","cefr":"B2","def":"a flower with a sweet smell that grows on a bush with thorns (= sharp points) on its stems","example":"a bunch of red roses"},{"w":"rosy","pos":"adj","cefr":"B2","def":"","example":""},{"w":"roughly","pos":"v","cefr":"B2","def":"approximately but not exactly","example":"Sales are up by roughly 10 per cent."},{"w":"round","pos":"adj","cefr":"B2","def":"having a shape like a circle or a ball","example":"a round plate"},{"w":"route","pos":"n","cefr":"B2","def":"a way that you follow to get from one place to another","example":"Which is the best route to take?"},{"w":"routine","pos":"n","cefr":"B2","def":"done or happening as a normal part of a particular job, situation or process","example":"routine enquiries/questions/tests/screening"},{"w":"royalty","pos":"n","cefr":"B2","def":"","example":""},{"w":"rub","pos":"v","cefr":"B2","def":"to move your hand, a cloth, etc., backwards and forwards over a surface while pressing it","example":"rub something, He sat up on the hard bunk and rubbed his eyes. "},{"w":"rubber","pos":"n","cefr":"B2","def":"made of rubber","example":"a rubber ball"},{"w":"rubble","pos":"n","cefr":"B2","def":"","example":""},{"w":"rug","pos":"n","cefr":"B2","def":"","example":""},{"w":"ruin","pos":"n","cefr":"B2","def":"the state or process of being destroyed or severely damaged","example":"A large number of churches fell into ruin after the revolution."},{"w":"ruinous","pos":"adj","cefr":"B2","def":"","example":""},{"w":"rural","pos":"adj","cefr":"B2","def":"connected with or like the countryside","example":"rural areas"},{"w":"rush","pos":"n","cefr":"B2","def":"a sudden strong movement or action","example":"rush for something, Shoppers made a rush for the exits."},{"w":"rusty","pos":"adj","cefr":"B2","def":"","example":""},{"w":"sag","pos":"n","cefr":"B2","def":"","example":""},{"w":"sage","pos":"n","cefr":"B2","def":"","example":""},{"w":"sail","pos":"v","cefr":"B2","def":"a sheet of strong cloth which the wind blows against to make a boat or ship travel through the water","example":"As the boat moved down the river the wind began to fill the sails."},{"w":"salary","pos":"n","cefr":"B2","def":"money that employees receive for doing their job, especially professional employees or people working in an office, usually paid every month","example":"an annual salary of $40 000"},{"w":"salesmanship","pos":"n","cefr":"B2","def":"","example":""},{"w":"salesperson","pos":"n","cefr":"B2","def":"","example":""},{"w":"saleswoman","pos":"n","cefr":"B2","def":"","example":""},{"w":"salon","pos":"n","cefr":"B2","def":"","example":""},{"w":"salsa","pos":"n","cefr":"B2","def":"","example":""},{"w":"salty","pos":"adj","cefr":"B2","def":"","example":""},{"w":"sample","pos":"n","cefr":"B2","def":"a number of people or things taken from a larger group and used in tests to provide information about the group","example":"The interviews were given to a random sample of students."},{"w":"sandstone","pos":"n","cefr":"B2","def":"","example":""},{"w":"sanitary","pos":"adj","cefr":"B2","def":"","example":""},{"w":"sanitation","pos":"n","cefr":"B2","def":"","example":""},{"w":"satellite","pos":"n","cefr":"B2","def":"an electronic device that is sent into space and moves around the earth or another planet. It is used for communicating by radio, television, etc. and for gathering information.","example":"a weather/communications/spy satellite "},{"w":"satisfaction","pos":"n","cefr":"B2","def":"the good feeling that you have when you have achieved something or when something that you wanted to happen does happen; something that gives you this feeling","example":"to gain/get/derive satisfaction from something"},{"w":"satisfactory","pos":"adj","cefr":"B2","def":"","example":""},{"w":"satisfied","pos":"adj","cefr":"B2","def":"pleased because you have achieved something or because something that you wanted to happen has happened","example":"a satisfied customer"},{"w":"satisfy","pos":"v","cefr":"B2","def":"to make somebody pleased by doing or giving them what they want","example":"Nothing satisfies him—he's always complaining."},{"w":"saving","pos":"n","cefr":"B2","def":"an amount of something such as time or money that you do not need to use or spend","example":"saving of something, Buy three and make a saving of 55p."},{"w":"savings","pos":"n","cefr":"B2","def":"","example":""},{"w":"scale","pos":"n","cefr":"B2","def":"the size or extent of something, especially when compared with something else","example":"on a … scale, They entertain on a large scale (= they hold expensive parties with a lot of guests)."},{"w":"scandal","pos":"n","cefr":"B2","def":"behaviour or an event that people think is morally or legally wrong and causes public feelings of shock or anger","example":"a series of sex scandals"},{"w":"scar","pos":"n","cefr":"B2","def":"","example":""},{"w":"scarcely","pos":"v","cefr":"B2","def":"","example":""},{"w":"scare","pos":"v","cefr":"B2","def":"a situation in which a lot of people are anxious or frightened about something","example":"a health scare"},{"w":"scarlet","pos":"n","cefr":"B2","def":"","example":""},{"w":"scenario","pos":"n","cefr":"B2","def":"a description of how things might happen in the future","example":"Let me suggest a possible scenario."},{"w":"scent","pos":"n","cefr":"B2","def":"","example":""},{"w":"schedule","pos":"n","cefr":"B2","def":"a plan that lists all the work that you have to do and when you must do each thing","example":"I have a hectic schedule for the next few days."}]}